xml_to_pydantic/__init__.py
xml_to_pydantic/model.py
xml_to_pydantic/py.typed
xml_to_pydantic/typing.py
xml_to_pydantic-0.2.dist-info/LICENSE
xml_to_pydantic-0.2.dist-info/METADATA
xml_to_pydantic-0.2.dist-info/WHEEL
xml_to_pydantic-0.2.dist-info/RECORD
